jks/__init__.py
jks/bks.py
jks/jks.py
jks/rfc2898.py
jks/rfc7292.py
jks/sun_crypto.py
jks/util.py
pyjks-19.0.0.dist-info/DESCRIPTION.rst
pyjks-19.0.0.dist-info/LICENSE.txt
pyjks-19.0.0.dist-info/METADATA
pyjks-19.0.0.dist-info/RECORD
pyjks-19.0.0.dist-info/WHEEL
pyjks-19.0.0.dist-info/metadata.json
pyjks-19.0.0.dist-info/top_level.txt
tests/expected/DSA2048.py
tests/expected/RSA1024.py
tests/expected/RSA2048_3certs.py
tests/expected/__init__.py
tests/expected/bks_christmas.py
tests/expected/bks_custom_entry_passwords.py
tests/expected/custom_entry_passwords.py
tests/expected/jks_non_ascii_password.py
