Metadata-Version: 2.0
Name: pyjks
Version: 19.0.0
Summary: Pure-Python Java Keystore (JKS) library
Home-page: http://github.com/kurtbrose/pyjks
Author: Kurt Rose, Jeroen De Ridder
Author-email: kurt@kurtrose.com
License: MIT
Keywords: JKS JCEKS java keystore security ssl
Platform: UNKNOWN
Classifier: Development Status :: 4 - Beta
Classifier: License :: OSI Approved :: MIT License
Classifier: Topic :: Utilities
Classifier: Topic :: Software Development :: Libraries
Classifier: Intended Audience :: Developers
Classifier: Programming Language :: Python :: 2.6
Classifier: Programming Language :: Python :: 2.7
Classifier: Programming Language :: Python :: 3.3
Classifier: Programming Language :: Python :: 3.4
Classifier: Programming Language :: Python :: 3.5
Classifier: Programming Language :: Python :: 3.6
Classifier: Programming Language :: Python :: Implementation :: PyPy
Requires-Dist: javaobj-py3
Requires-Dist: pyasn1 (>=0.3.5)
Requires-Dist: pyasn1-modules
Requires-Dist: pycryptodomex
Requires-Dist: twofish
